// class version 52.0 (52)
// access flags 0x31
public final class BubbleSortKotlin {

  // compiled from: BubbleSortKotlin.kt

  @Lkotlin/Metadata;(mv={1, 7, 1}, k=1, xi=48, d1={"\u0000\u001a\n\u0002\u0018\u0002\n\u0002\u0010\u0000\n\u0002\u0008\u0002\n\u0002\u0010\u0002\n\u0000\n\u0002\u0010\u0015\n\u0002\u0008\u0003\u0018\u0000 \u00082\u00020\u0001:\u0001\u0008B\u0005\u00a2\u0006\u0002\u0010\u0002J\u000e\u0010\u0003\u001a\u00020\u00042\u0006\u0010\u0005\u001a\u00020\u0006J\u000e\u0010\u0007\u001a\u00020\u00042\u0006\u0010\u0005\u001a\u00020\u0006\u00a8\u0006\u0009"}, d2={"LBubbleSortKotlin;", "", "()V", "bubbleSort", "", "arr", "", "printArray", "Companion", "Lab3"})
  // access flags 0x19
  public final static INNERCLASS BubbleSortKotlin$Companion BubbleSortKotlin Companion

  // access flags 0x19
  public final static LBubbleSortKotlin$Companion; Companion
  @Lorg/jetbrains/annotations/NotNull;() // invisible

  // access flags 0x1
  public <init>()V
   L0
    LINENUMBER 1 L0
    ALOAD 0
    INVOKESPECIAL java/lang/Object.<init> ()V
    RETURN
   L1
    LOCALVARIABLE this LBubbleSortKotlin; L0 L1 0
    MAXSTACK = 1
    MAXLOCALS = 1

  // access flags 0x11
  public final bubbleSort([I)V
    // annotable parameter count: 1 (invisible)
    @Lorg/jetbrains/annotations/NotNull;() // invisible, parameter 0
   L0
    ALOAD 1
    LDC "arr"
    INVOKESTATIC kotlin/jvm/internal/Intrinsics.checkNotNullParameter (Ljava/lang/Object;Ljava/lang/String;)V
   L1
    LINENUMBER 3 L1
    ALOAD 1
    ARRAYLENGTH
    ISTORE 2
   L2
    LINENUMBER 4 L2
    ICONST_0
    ISTORE 3
   L3
    ILOAD 2
    ICONST_1
    ISUB
    ISTORE 4
   L4
   FRAME APPEND [I I I]
    ILOAD 3
    ILOAD 4
    IF_ICMPGE L5
    ICONST_0
    ISTORE 5
   L6
    ILOAD 2
    ILOAD 3
    ISUB
    ICONST_1
    ISUB
    ISTORE 6
   L7
   FRAME APPEND [I I]
    ILOAD 5
    ILOAD 6
    IF_ICMPGE L8
    ALOAD 1
    ILOAD 5
    IALOAD
    ALOAD 1
    ILOAD 5
    ICONST_1
    IADD
    IALOAD
    IF_ICMPLE L9
   L10
    LINENUMBER 5 L10
    ALOAD 1
    ILOAD 5
    IALOAD
    ISTORE 7
   L11
    LINENUMBER 6 L11
    ALOAD 1
    ILOAD 5
    ALOAD 1
    ILOAD 5
    ICONST_1
    IADD
    IALOAD
    IASTORE
   L12
    LINENUMBER 7 L12
    ALOAD 1
    ILOAD 5
    ICONST_1
    IADD
    ILOAD 7
    IASTORE
   L9
    LINENUMBER 4 L9
   FRAME SAME
    IINC 5 1
    GOTO L7
   L8
   FRAME SAME
    IINC 3 1
    GOTO L4
   L5
    LINENUMBER 9 L5
   FRAME CHOP 2
    RETURN
   L13
    LOCALVARIABLE temp I L11 L9 7
    LOCALVARIABLE j I L6 L8 5
    LOCALVARIABLE i I L3 L5 3
    LOCALVARIABLE n I L2 L13 2
    LOCALVARIABLE this LBubbleSortKotlin; L0 L13 0
    LOCALVARIABLE arr [I L0 L13 1
    MAXSTACK = 5
    MAXLOCALS = 8

  // access flags 0x11
  public final printArray([I)V
    // annotable parameter count: 1 (invisible)
    @Lorg/jetbrains/annotations/NotNull;() // invisible, parameter 0
   L0
    ALOAD 1
    LDC "arr"
    INVOKESTATIC kotlin/jvm/internal/Intrinsics.checkNotNullParameter (Ljava/lang/Object;Ljava/lang/String;)V
   L1
    LINENUMBER 12 L1
    ICONST_0
    ISTORE 2
    ALOAD 1
    ARRAYLENGTH
    ISTORE 3
   L2
   FRAME APPEND [I I]
    ILOAD 2
    ILOAD 3
    IF_ICMPGE L3
    ALOAD 1
    ILOAD 2
    IALOAD
    ISTORE 4
   L4
    NEW java/lang/StringBuilder
    DUP
    INVOKESPECIAL java/lang/StringBuilder.<init> ()V
    ILOAD 4
    INVOKEVIRTUAL java/lang/StringBuilder.append (I)Ljava/lang/StringBuilder;
    BIPUSH 32
    INVOKEVIRTUAL java/lang/StringBuilder.append (C)Ljava/lang/StringBuilder;
    INVOKEVIRTUAL java/lang/StringBuilder.toString ()Ljava/lang/String;
    GETSTATIC java/lang/System.out : Ljava/io/PrintStream;
    SWAP
    INVOKEVIRTUAL java/io/PrintStream.print (Ljava/lang/Object;)V
   L5
    LINENUMBER 12 L5
    IINC 2 1
    GOTO L2
   L3
    LINENUMBER 13 L3
   FRAME SAME
    GETSTATIC java/lang/System.out : Ljava/io/PrintStream;
    INVOKEVIRTUAL java/io/PrintStream.println ()V
   L6
    LINENUMBER 14 L6
    RETURN
   L7
    LOCALVARIABLE j I L4 L5 4
    LOCALVARIABLE this LBubbleSortKotlin; L0 L7 0
    LOCALVARIABLE arr [I L0 L7 1
    MAXSTACK = 2
    MAXLOCALS = 5

  // access flags 0x19
  public final static main([Ljava/lang/String;)V
  @Lkotlin/jvm/JvmStatic;()
    // annotable parameter count: 1 (invisible)
    @Lorg/jetbrains/annotations/NotNull;() // invisible, parameter 0
   L0
    GETSTATIC BubbleSortKotlin.Companion : LBubbleSortKotlin$Companion;
    ALOAD 0
    INVOKEVIRTUAL BubbleSortKotlin$Companion.main ([Ljava/lang/String;)V
    RETURN
   L1
    LOCALVARIABLE args [Ljava/lang/String; L0 L1 0
    MAXSTACK = 2
    MAXLOCALS = 1

  // access flags 0x8
  static <clinit>()V
    NEW BubbleSortKotlin$Companion
    DUP
    ACONST_NULL
    INVOKESPECIAL BubbleSortKotlin$Companion.<init> (Lkotlin/jvm/internal/DefaultConstructorMarker;)V
    PUTSTATIC BubbleSortKotlin.Companion : LBubbleSortKotlin$Companion;
    RETURN
    MAXSTACK = 3
    MAXLOCALS = 0
}
